{"assets":{"23F3D95220404BC1D064E209F5E1E136":{"type":"texture","index":0,"assetRequest":{"type":"slide","state":"outgoing","slide":"F0CCB39A-304F-432B-AFD2-6405E1829CE8"},"url":{"web":"assets/F0CCB39A-304F-432B-AFD2-6405E1829CE8.svgmap"},"width":1024,"height":768},"08726A5817D31687CA89C165944D7BB5":{"type":"texture","index":1,"assetRequest":{"type":"slide","state":"incoming","slide":"895D8BE2-8655-4F3B-8B36-D161B4551A40"},"url":{"web":"assets/F0CCB39A-304F-432B-AFD2-6405E1829CE8.svgmap"},"width":1024,"height":768}},"events":[{"effects":[{"beginTime":0,"baseLayer":{"animations":[],"initialState":{"affineTransform":[1,0,0,1,0,0],"masksToBounds":false,"rotation":0,"scale":1,"position":{"pointX":512,"pointY":384},"width":1024,"sublayerTransform":[1,0,0,0,0,1,0,0,0,0,1,0,0,0,0,1],"contentsRect":{"y":0,"x":0,"width":1,"height":1},"opacity":1,"edgeAntialiasingMask":251658240,"height":768,"hidden":false,"anchorPoint":{"pointX":0.5,"pointY":0.5}},"objectID":"0","layers":[{"animations":[],"initialState":{"affineTransform":[1,0,0,1,0,0],"masksToBounds":false,"rotation":0,"scale":1,"position":{"pointX":512,"pointY":384},"width":1024,"sublayerTransform":[1,0,0,0,0,1,0,0,0,0,1,-0.0004922987690640373,0,0,0,1],"contentsRect":{"y":0,"x":0,"width":1,"height":1},"opacity":1,"edgeAntialiasingMask":251658240,"height":768,"hidden":false,"anchorPoint":{"pointX":0.5,"pointY":0.5}},"layers":[{"animations":[],"layers":[],"texturedRectangle":{"isBackgroundTexture":false,"singleTextureOpacity":1,"textureType":0,"textBaseline":0,"textXHeight":0,"isVerticalText":false},"initialState":{"affineTransform":[1,0,0,1,0,0],"masksToBounds":false,"rotation":0,"scale":1,"position":{"pointX":512,"pointY":384},"width":1024,"sublayerTransform":[1,0,0,0,0,1,0,0,0,0,1,0,0,0,0,1],"contentsRect":{"y":0,"x":0,"width":1,"height":1},"opacity":1,"edgeAntialiasingMask":0,"height":768,"hidden":false,"anchorPoint":{"pointX":0.5,"pointY":0.5}},"texture":"08726A5817D31687CA89C165944D7BB5"},{"animations":[{"timeOffset":0,"from":{"scalar":false},"beginTime":0,"repeatCount":0,"fillMode":"both","property":"hidden","autoreverses":false,"duration":0.01,"to":{"scalar":true}}],"layers":[],"texturedRectangle":{"isBackgroundTexture":false,"singleTextureOpacity":1,"textureType":0,"textBaseline":0,"textXHeight":0,"isVerticalText":false},"initialState":{"affineTransform":[1,0,0,1,0,0],"masksToBounds":false,"rotation":0,"scale":1,"position":{"pointX":512,"pointY":384},"width":1024,"sublayerTransform":[1,0,0,0,0,1,0,0,0,0,1,0,0,0,0,1],"contentsRect":{"y":0,"x":0,"width":1,"height":1},"opacity":1,"edgeAntialiasingMask":0,"height":768,"hidden":false,"anchorPoint":{"pointX":0.5,"pointY":0.5}},"texture":"23F3D95220404BC1D064E209F5E1E136"}]}]},"effects":[],"duration":0.01,"type":"transition","name":"none","objectID":"0"}],"automaticPlay":false,"hyperlinks":[],"accessibility":[{"text":"cret4","targetRectangle":{"y":163.0083312988281,"x":2.331013679504395,"width":580.84375,"height":484.6562500000001}},{"text":"Forcing parameters","targetRectangle":{"y":7.462387084960938,"x":17.49236679077148,"width":507.19921875,"height":74}},{"text":"GA paleo atlas","targetRectangle":{"y":660.9399408629153,"x":66.77606729290892,"width":124.7166676402092,"height":19}},{"text":"It’s difficult to get such a model to match paleo-shorelines mapped based on geological data","targetRectangle":{"y":168.6333475112915,"x":594.3723161220551,"width":376.13525390625,"height":106.1999952793121}},{"text":"Initial topographic condition at model starting time is uncertain","targetRectangle":{"y":274.8333427906036,"x":594.3723161220551,"width":412.75634765625,"height":88.79999685287476}},{"text":"Difficult to take into account regional crustal/lithospheric deformation, thickening or thinning, resulting in uplift (or subsidence)","targetRectangle":{"y":363.6333396434784,"x":594.3723161220551,"width":408.55712890625,"height":159.5999937057495}},{"text":"Cretaceous subduction history and mantle structure north of Australia is uncertain","targetRectangle":{"y":523.2333333492279,"x":594.3723161220551,"width":405.74951171875,"height":124.1999952793121}}],"baseLayer":{"animations":[],"initialState":{"affineTransform":[1,0,0,1,0,0],"masksToBounds":false,"rotation":0,"scale":1,"position":{"pointX":512,"pointY":384},"width":1024,"sublayerTransform":[1,0,0,0,0,1,0,0,0,0,1,0,0,0,0,1],"contentsRect":{"y":0,"x":0,"width":1,"height":1},"opacity":1,"edgeAntialiasingMask":251658240,"height":768,"hidden":false,"anchorPoint":{"pointX":0.5,"pointY":0.5}},"objectID":"0","layers":[{"animations":[],"initialState":{"affineTransform":[1,0,0,1,0,0],"masksToBounds":false,"rotation":0,"scale":1,"position":{"pointX":512,"pointY":384},"width":1024,"sublayerTransform":[1,0,0,0,0,1,0,0,0,0,1,-0.0004922987690640373,0,0,0,1],"contentsRect":{"y":0,"x":0,"width":1,"height":1},"opacity":1,"edgeAntialiasingMask":251658240,"height":768,"hidden":false,"anchorPoint":{"pointX":0.5,"pointY":0.5}},"layers":[{"animations":[],"layers":[],"texturedRectangle":{"isBackgroundTexture":false,"singleTextureOpacity":1,"textureType":0,"textBaseline":0,"textXHeight":0,"isVerticalText":false},"initialState":{"affineTransform":[1,0,0,1,0,0],"masksToBounds":false,"rotation":0,"scale":1,"position":{"pointX":512,"pointY":384},"width":1024,"sublayerTransform":[1,0,0,0,0,1,0,0,0,0,1,0,0,0,0,1],"contentsRect":{"y":0,"x":0,"width":1,"height":1},"opacity":1,"edgeAntialiasingMask":0,"height":768,"hidden":false,"anchorPoint":{"pointX":0.5,"pointY":0.5}},"texture":"23F3D95220404BC1D064E209F5E1E136"}]}]}}]}