{"assets":{"C1B96BE51239F73ECB5E381560DDA59B":{"type":"texture","index":0,"assetRequest":{"type":"slide","state":"outgoing","slide":"D9F5E6C2-3D3F-49D7-B838-A687FC34320A"},"url":{"web":"assets/D9F5E6C2-3D3F-49D7-B838-A687FC34320A.svgmap"},"width":1024,"height":768},"BC44EDF1A4FFAE4E038BA5D0BC3188AB":{"type":"texture","index":1,"assetRequest":{"type":"slide","state":"incoming","slide":"3EFA3A71-3417-4081-A788-81F174C4C763"},"url":{"web":"assets/D9F5E6C2-3D3F-49D7-B838-A687FC34320A.svgmap"},"width":1024,"height":768}},"events":[{"effects":[{"beginTime":0,"baseLayer":{"animations":[],"initialState":{"affineTransform":[1,0,0,1,0,0],"masksToBounds":false,"rotation":0,"scale":1,"position":{"pointX":512,"pointY":384},"width":1024,"sublayerTransform":[1,0,0,0,0,1,0,0,0,0,1,0,0,0,0,1],"contentsRect":{"y":0,"x":0,"width":1,"height":1},"opacity":1,"edgeAntialiasingMask":251658240,"height":768,"hidden":false,"anchorPoint":{"pointX":0.5,"pointY":0.5}},"objectID":"0","layers":[{"animations":[],"initialState":{"affineTransform":[1,0,0,1,0,0],"masksToBounds":false,"rotation":0,"scale":1,"position":{"pointX":512,"pointY":384},"width":1024,"sublayerTransform":[1,0,0,0,0,1,0,0,0,0,1,-0.0004922987690640373,0,0,0,1],"contentsRect":{"y":0,"x":0,"width":1,"height":1},"opacity":1,"edgeAntialiasingMask":251658240,"height":768,"hidden":false,"anchorPoint":{"pointX":0.5,"pointY":0.5}},"layers":[{"animations":[],"layers":[],"texturedRectangle":{"isBackgroundTexture":false,"singleTextureOpacity":1,"textureType":0,"textBaseline":0,"textXHeight":0,"isVerticalText":false},"initialState":{"affineTransform":[1,0,0,1,0,0],"masksToBounds":false,"rotation":0,"scale":1,"position":{"pointX":512,"pointY":384},"width":1024,"sublayerTransform":[1,0,0,0,0,1,0,0,0,0,1,0,0,0,0,1],"contentsRect":{"y":0,"x":0,"width":1,"height":1},"opacity":1,"edgeAntialiasingMask":0,"height":768,"hidden":false,"anchorPoint":{"pointX":0.5,"pointY":0.5}},"texture":"BC44EDF1A4FFAE4E038BA5D0BC3188AB"},{"animations":[{"timeOffset":0,"from":{"scalar":false},"beginTime":0,"repeatCount":0,"fillMode":"both","property":"hidden","autoreverses":false,"duration":0.01,"to":{"scalar":true}}],"layers":[],"texturedRectangle":{"isBackgroundTexture":false,"singleTextureOpacity":1,"textureType":0,"textBaseline":0,"textXHeight":0,"isVerticalText":false},"initialState":{"affineTransform":[1,0,0,1,0,0],"masksToBounds":false,"rotation":0,"scale":1,"position":{"pointX":512,"pointY":384},"width":1024,"sublayerTransform":[1,0,0,0,0,1,0,0,0,0,1,0,0,0,0,1],"contentsRect":{"y":0,"x":0,"width":1,"height":1},"opacity":1,"edgeAntialiasingMask":0,"height":768,"hidden":false,"anchorPoint":{"pointX":0.5,"pointY":0.5}},"texture":"C1B96BE51239F73ECB5E381560DDA59B"}]}]},"effects":[],"duration":0.01,"type":"transition","name":"none","objectID":"0"}],"automaticPlay":false,"hyperlinks":[],"accessibility":[{"text":"r2_250.png","targetRectangle":{"y":471.0113403655319,"x":780.6084136962891,"width":242.4930813572897,"height":301.7836343050003}},{"text":"no Eastern Highlands","targetRectangle":{"y":405.5000000596046,"x":547.612548828125,"width":133.0349999374151,"height":17}},{"text":"f120.png","targetRectangle":{"y":147.1630535586168,"x":773.7935028076172,"width":234.8898022600479,"height":293.5040559528713}},{"text":"c2_40.png","targetRectangle":{"y":152.4517021179199,"x":28.70388746261597,"width":225.6721073196468,"height":302.7552443418756}},{"text":"0 Ma","targetRectangle":{"y":708.2876586914062,"x":821.4037857055664,"width":42.23974609375,"height":23}},{"text":"c120.png","targetRectangle":{"y":140.9319948028633,"x":263.3580894470215,"width":258.2556411672849,"height":323.3228234629423}},{"text":"Main Catchments Delimitation","targetRectangle":{"y":741.0570219755173,"x":98.49906635284424,"width":325.473,"height":31}},{"text":"0 Ma","targetRectangle":{"y":709.2822265625,"x":334.0363235473633,"width":42.23974609375,"height":23}},{"text":"90 Ma","targetRectangle":{"y":379.5415954589844,"x":816.1203308105469,"width":52.806640625,"height":23}},{"text":"c2_200.png","targetRectangle":{"y":457.1041283433153,"x":14.75225162506104,"width":244.1689092846773,"height":305.1693385804321}},{"text":"50 Ma","targetRectangle":{"y":708.5042724609375,"x":75.12036895751953,"width":52.806640625,"height":23}},{"text":"no Eastern Highlands","targetRectangle":{"y":405.5000000596046,"x":16.27921581268311,"width":133.0349999374151,"height":17}},{"text":"r2_40.png","targetRectangle":{"y":147.1727455556393,"x":535.744873046875,"width":227.2707693912798,"height":296.0441543792404}},{"text":"50 Ma","targetRectangle":{"y":707.5097045898438,"x":559.260986328125,"width":52.806640625,"height":23}},{"text":"130 Ma","targetRectangle":{"y":379.5415954589844,"x":69.83692169189453,"width":63.37353515625,"height":23}},{"text":"Drainage organisation & Catchment stability","targetRectangle":{"y":-1.870948791503906,"x":3.80389404296875,"width":944.6572265625,"height":148}},{"text":"r2_200.png","targetRectangle":{"y":467.6656672920228,"x":527.8908996582031,"width":244.6875,"height":305.1983387705866}},{"text":"Main Drainage Network","targetRectangle":{"y":107.0570219755173,"x":617.9755926132202,"width":258.52,"height":31}},{"text":"c2_250.png","targetRectangle":{"y":455.3873010543994,"x":258.6114196777344,"width":255.1773458245298,"height":315.9329027506756}},{"text":"130 Ma","targetRectangle":{"y":379.5415954589844,"x":563.8368835449219,"width":63.37353515625,"height":23}},{"text":"90 Ma","targetRectangle":{"y":379.5415954589844,"x":328.7528686523438,"width":52.806640625,"height":23}}],"baseLayer":{"animations":[],"initialState":{"affineTransform":[1,0,0,1,0,0],"masksToBounds":false,"rotation":0,"scale":1,"position":{"pointX":512,"pointY":384},"width":1024,"sublayerTransform":[1,0,0,0,0,1,0,0,0,0,1,0,0,0,0,1],"contentsRect":{"y":0,"x":0,"width":1,"height":1},"opacity":1,"edgeAntialiasingMask":251658240,"height":768,"hidden":false,"anchorPoint":{"pointX":0.5,"pointY":0.5}},"objectID":"0","layers":[{"animations":[],"initialState":{"affineTransform":[1,0,0,1,0,0],"masksToBounds":false,"rotation":0,"scale":1,"position":{"pointX":512,"pointY":384},"width":1024,"sublayerTransform":[1,0,0,0,0,1,0,0,0,0,1,-0.0004922987690640373,0,0,0,1],"contentsRect":{"y":0,"x":0,"width":1,"height":1},"opacity":1,"edgeAntialiasingMask":251658240,"height":768,"hidden":false,"anchorPoint":{"pointX":0.5,"pointY":0.5}},"layers":[{"animations":[],"layers":[],"texturedRectangle":{"isBackgroundTexture":false,"singleTextureOpacity":1,"textureType":0,"textBaseline":0,"textXHeight":0,"isVerticalText":false},"initialState":{"affineTransform":[1,0,0,1,0,0],"masksToBounds":false,"rotation":0,"scale":1,"position":{"pointX":512,"pointY":384},"width":1024,"sublayerTransform":[1,0,0,0,0,1,0,0,0,0,1,0,0,0,0,1],"contentsRect":{"y":0,"x":0,"width":1,"height":1},"opacity":1,"edgeAntialiasingMask":0,"height":768,"hidden":false,"anchorPoint":{"pointX":0.5,"pointY":0.5}},"texture":"C1B96BE51239F73ECB5E381560DDA59B"}]}]}}]}